{
  "$schema": "https://ui.shadcn.com/schema/registry-item.json",
  "name": "pattern-button-outline-1",
  "type": "registry:component",
  "title": "Button Outline 1",
  "description": "A button pattern: button-outline-1",
  "registryDependencies": [],
  "files": [
    {
      "path": "registry/new-york/patterns/button/outline/button-outline-1.tsx",
      "content": "import { Button } from \"@/components/ui/button\";\n\nexport const title = \"Button with Text\";\n\nconst Example = () => <Button variant=\"outline\">Button</Button>;\n\nexport default Example;\n",
      "type": "registry:component"
    }
  ]
}