{
  "$schema": "https://ui.shadcn.com/schema/registry-item.json",
  "name": "pattern-tabs-content-3",
  "type": "registry:component",
  "title": "Tabs Content 3",
  "description": "A tabs pattern: tabs-content-3",
  "registryDependencies": [],
  "files": [
    {
      "path": "registry/new-york/patterns/tabs/content/tabs-content-3.tsx",
      "content": "import { Badge } from \"@/components/ui/badge\";\nimport { ScrollArea } from \"@/components/ui/scroll-area\";\nimport { Tabs, TabsContent, TabsList, TabsTrigger } from \"@/components/ui/tabs\";\n\nexport const title = \"Tabs with Tables\";\n\nconst users = Array.from({ length: 8 }, (_, i) => ({\n  id: i + 1,\n  name: `User ${i + 1}`,\n  email: `user${i + 1}@example.com`,\n  role: i % 3 === 0 ? \"Admin\" : i % 2 === 0 ? \"Editor\" : \"Viewer\",\n  status: i % 2 === 0 ? \"Active\" : \"Inactive\",\n}));\n\nconst Example = () => (\n  <Tabs className=\"w-full max-w-2xl\" defaultValue=\"all\">\n    <TabsList>\n      <TabsTrigger value=\"all\">All Users</TabsTrigger>\n      <TabsTrigger value=\"active\">Active</TabsTrigger>\n      <TabsTrigger value=\"inactive\">Inactive</TabsTrigger>\n    </TabsList>\n    <TabsContent value=\"all\">\n      <div className=\"rounded-lg border bg-card shadow-sm\">\n        <ScrollArea className=\"h-[400px]\">\n          <table className=\"w-full\">\n            <thead className=\"border-b\">\n              <tr>\n                <th className=\"px-4 py-3 text-left font-medium text-sm\">\n                  Name\n                </th>\n                <th className=\"px-4 py-3 text-left font-medium text-sm\">\n                  Email\n                </th>\n                <th className=\"px-4 py-3 text-left font-medium text-sm\">\n                  Role\n                </th>\n                <th className=\"px-4 py-3 text-left font-medium text-sm\">\n                  Status\n                </th>\n              </tr>\n            </thead>\n            <tbody>\n              {users.map((user) => (\n                <tr className=\"border-b\" key={user.id}>\n                  <td className=\"px-4 py-3 text-sm\">{user.name}</td>\n                  <td className=\"px-4 py-3 text-muted-foreground text-sm\">\n                    {user.email}\n                  </td>\n                  <td className=\"px-4 py-3 text-sm\">{user.role}</td>\n                  <td className=\"px-4 py-3\">\n                    <Badge\n                      variant={\n                        user.status === \"Active\" ? \"default\" : \"secondary\"\n                      }\n                    >\n                      {user.status}\n                    </Badge>\n                  </td>\n                </tr>\n              ))}\n            </tbody>\n          </table>\n        </ScrollArea>\n      </div>\n    </TabsContent>\n    <TabsContent value=\"active\">\n      <div className=\"rounded-lg border bg-card shadow-sm\">\n        <ScrollArea className=\"h-[400px]\">\n          <table className=\"w-full\">\n            <thead className=\"border-b\">\n              <tr>\n                <th className=\"px-4 py-3 text-left font-medium text-sm\">\n                  Name\n                </th>\n                <th className=\"px-4 py-3 text-left font-medium text-sm\">\n                  Email\n                </th>\n                <th className=\"px-4 py-3 text-left font-medium text-sm\">\n                  Role\n                </th>\n                <th className=\"px-4 py-3 text-left font-medium text-sm\">\n                  Status\n                </th>\n              </tr>\n            </thead>\n            <tbody>\n              {users\n                .filter((user) => user.status === \"Active\")\n                .map((user) => (\n                  <tr className=\"border-b\" key={user.id}>\n                    <td className=\"px-4 py-3 text-sm\">{user.name}</td>\n                    <td className=\"px-4 py-3 text-muted-foreground text-sm\">\n                      {user.email}\n                    </td>\n                    <td className=\"px-4 py-3 text-sm\">{user.role}</td>\n                    <td className=\"px-4 py-3\">\n                      <Badge>Active</Badge>\n                    </td>\n                  </tr>\n                ))}\n            </tbody>\n          </table>\n        </ScrollArea>\n      </div>\n    </TabsContent>\n    <TabsContent value=\"inactive\">\n      <div className=\"rounded-lg border bg-card shadow-sm\">\n        <ScrollArea className=\"h-[400px]\">\n          <table className=\"w-full\">\n            <thead className=\"border-b\">\n              <tr>\n                <th className=\"px-4 py-3 text-left font-medium text-sm\">\n                  Name\n                </th>\n                <th className=\"px-4 py-3 text-left font-medium text-sm\">\n                  Email\n                </th>\n                <th className=\"px-4 py-3 text-left font-medium text-sm\">\n                  Role\n                </th>\n                <th className=\"px-4 py-3 text-left font-medium text-sm\">\n                  Status\n                </th>\n              </tr>\n            </thead>\n            <tbody>\n              {users\n                .filter((user) => user.status === \"Inactive\")\n                .map((user) => (\n                  <tr className=\"border-b\" key={user.id}>\n                    <td className=\"px-4 py-3 text-sm\">{user.name}</td>\n                    <td className=\"px-4 py-3 text-muted-foreground text-sm\">\n                      {user.email}\n                    </td>\n                    <td className=\"px-4 py-3 text-sm\">{user.role}</td>\n                    <td className=\"px-4 py-3\">\n                      <Badge variant=\"secondary\">Inactive</Badge>\n                    </td>\n                  </tr>\n                ))}\n            </tbody>\n          </table>\n        </ScrollArea>\n      </div>\n    </TabsContent>\n  </Tabs>\n);\n\nexport default Example;\n",
      "type": "registry:component"
    }
  ]
}