{
  "$schema": "https://ui.shadcn.com/schema/registry-item.json",
  "name": "pattern-drawer-right-3",
  "type": "registry:component",
  "title": "Drawer Right 3",
  "description": "A drawer pattern: drawer-right-3",
  "registryDependencies": [],
  "files": [
    {
      "path": "registry/new-york/patterns/drawer/right/drawer-right-3.tsx",
      "content": "\"use client\";\n\nimport { Settings } from \"lucide-react\";\nimport { Button } from \"@/components/ui/button\";\nimport {\n  Drawer,\n  DrawerClose,\n  DrawerContent,\n  DrawerDescription,\n  DrawerFooter,\n  DrawerHeader,\n  DrawerTitle,\n  DrawerTrigger,\n} from \"@/components/ui/drawer\";\nimport { Label } from \"@/components/ui/label\";\nimport { Switch } from \"@/components/ui/switch\";\n\nexport const title = \"Right Drawer Settings Panel\";\n\nconst Example = () => (\n  <Drawer direction=\"right\">\n    <DrawerTrigger asChild>\n      <Button size=\"icon\" variant=\"outline\">\n        <Settings className=\"h-4 w-4\" />\n      </Button>\n    </DrawerTrigger>\n    <DrawerContent>\n      <DrawerHeader>\n        <DrawerTitle>Settings</DrawerTitle>\n        <DrawerDescription>Manage your preferences</DrawerDescription>\n      </DrawerHeader>\n      <div className=\"space-y-6 p-4\">\n        <div className=\"space-y-4\">\n          <h4 className=\"font-medium text-sm\">Notifications</h4>\n          <div className=\"space-y-3\">\n            <div className=\"flex items-center justify-between\">\n              <Label className=\"text-sm\" htmlFor=\"email-notifs\">\n                Email notifications\n              </Label>\n              <Switch id=\"email-notifs\" />\n            </div>\n            <div className=\"flex items-center justify-between\">\n              <Label className=\"text-sm\" htmlFor=\"push-notifs\">\n                Push notifications\n              </Label>\n              <Switch defaultChecked id=\"push-notifs\" />\n            </div>\n            <div className=\"flex items-center justify-between\">\n              <Label className=\"text-sm\" htmlFor=\"sms-notifs\">\n                SMS notifications\n              </Label>\n              <Switch id=\"sms-notifs\" />\n            </div>\n          </div>\n        </div>\n        <div className=\"space-y-4\">\n          <h4 className=\"font-medium text-sm\">Privacy</h4>\n          <div className=\"space-y-3\">\n            <div className=\"flex items-center justify-between\">\n              <Label className=\"text-sm\" htmlFor=\"profile-visible\">\n                Profile visible\n              </Label>\n              <Switch defaultChecked id=\"profile-visible\" />\n            </div>\n            <div className=\"flex items-center justify-between\">\n              <Label className=\"text-sm\" htmlFor=\"show-activity\">\n                Show activity\n              </Label>\n              <Switch defaultChecked id=\"show-activity\" />\n            </div>\n          </div>\n        </div>\n      </div>\n      <DrawerFooter>\n        <Button>Save Changes</Button>\n        <DrawerClose asChild>\n          <Button variant=\"outline\">Cancel</Button>\n        </DrawerClose>\n      </DrawerFooter>\n    </DrawerContent>\n  </Drawer>\n);\n\nexport default Example;\n",
      "type": "registry:component"
    }
  ]
}